pyrootmancer/__init__.py
pyrootmancer/data/data_preprocessing.py
pyrootmancer/features/feature_scaling.py
pyrootmancer/features/instance_segmentation.py
pyrootmancer/features/robot_control.py
pyrootmancer/features/robotics/custom.urdf
pyrootmancer/features/robotics/cv_pipeline.py
pyrootmancer/features/robotics/meshes/base_link.stl
pyrootmancer/features/robotics/meshes/gantry_x1.stl
pyrootmancer/features/robotics/meshes/gantry_y1.stl
pyrootmancer/features/robotics/meshes/gantry_z1.stl
pyrootmancer/features/robotics/meshes copy/base_link.stl
pyrootmancer/features/robotics/meshes copy/gantry_x1.stl
pyrootmancer/features/robotics/meshes copy/gantry_y1.stl
pyrootmancer/features/robotics/meshes copy/gantry_z1.stl
pyrootmancer/features/robotics/ot2_gym_wrapper.py
pyrootmancer/features/robotics/ot_2_simulation_v6.urdf
pyrootmancer/features/robotics/robotics.py
pyrootmancer/features/robotics/root_tips_coordinates.csv
pyrootmancer/features/robotics/sim_class.py
pyrootmancer/features/root_coord_extraction.py
pyrootmancer/features/root_length.py
pyrootmancer/models/model_definitions.py
pyrootmancer/models/model_evaluation.py
pyrootmancer/models/model_training.py
pyrootmancer/README.md
pyrootmancer/test
pyrootmancer/utils/configuration.py
pyrootmancer-0.2.0.dist-info/LICENCE
pyrootmancer-0.2.0.dist-info/METADATA
pyrootmancer-0.2.0.dist-info/WHEEL
pyrootmancer-0.2.0.dist-info/RECORD
